pantherapy/__about__.py
pantherapy/__init__.py
pantherapy/panthera.cp37-win_amd64.pyd
pantherapy/reach.py
pantherapy/relation.py
pantherapy-0.0.3.dev0.dist-info/LICENSE
pantherapy-0.0.3.dev0.dist-info/METADATA
pantherapy-0.0.3.dev0.dist-info/WHEEL
pantherapy-0.0.3.dev0.dist-info/top_level.txt
pantherapy-0.0.3.dev0.dist-info/RECORD
