Metadata-Version: 2.1
Name: pantherapy
Version: 0.0.3.dev0
Summary: 1D hydraulics
Home-page: https://github.com/mmdski/panthera-undue
Author: Marian Domanski
Author-email: mmdski@gmail.com
License: GPLv3
Platform: UNKNOWN
Classifier: Development Status :: 1 - Planning
Classifier: Intended Audience :: Science/Research
Classifier: Programming Language :: C
Classifier: Programming Language :: Python :: 3
Classifier: License :: OSI Approved :: GNU General Public License v3 (GPLv3)
Classifier: Topic :: Scientific/Engineering :: Hydrology
Requires-Python: >=3.6
Requires-Dist: matplotlib
Requires-Dist: numpy
Requires-Dist: scipy
